examples/__init__.py
miniai/__init__.py
miniai/config.py
miniai/core.py
miniai/providers/__init__.py
miniai/providers/anthropic.py
miniai/providers/base.py
miniai/providers/constants.py
miniai/providers/mock.py
miniai/providers/openai.py
miniai-0.1.1.dist-info/licenses/LICENSE
miniai-0.1.1.dist-info/METADATA
miniai-0.1.1.dist-info/WHEEL
miniai-0.1.1.dist-info/top_level.txt
miniai-0.1.1.dist-info/RECORD
